{
  "metadata": {
    "audio": {
      "multichannelVocals": false,
      "needVoices": true,
      "bpm": 150,
      "timeSignature": [
        4,
        4
      ],
      "name": "Pico",
      "instrumental": {
        "inst": "Inst.ogg"
      },
      "vocals": {
        "vocals": "Voices.ogg"
      }
    },
    "stage": "philly",
    "events": true,
    "speed": 1.2,
    "skin": "Funkin",
    "opponents": [
      "pico"
    ],
    "players": [
      "bf"
    ],
    "spectator": [
      "gf"
    ],
    "credits": []
  },
  "notes": [
    {
      "t": 3800,
      "d": 2,
      "l": 0,
      "p": 0,
      "k": "default"
    },
    {
      "t": 4600,
      "d": 0,
      "l": 0,
      "p": 0,
      "k": "default"
    },
    {
      "t": 5000,
      "d": 0,
      "l": 0,
      "p": 0,
      "k": "default"
    },
    {
      "t": 5400,
      "d": 2,
      "l": 0,
      "p": 0,
      "k": "default"
    },
    {
      "t": 6200,
      "d": 0,
      "l": 0,
      "p": 0,
      "k": "default"
    },
    {
      "t": 7000,
      "d": 2,
      "l": 0,
      "p": 0,
      "k": "default"
    },
    {
      "t": 7800,
      "d": 0,
      "l": 0,
      "p": 0,
      "k": "default"
    },
    {
      "t": 8200,
      "d": 0,
      "l": 0,
      "p": 0,
      "k": "default"
    },
    {
      "t": 8600,
      "d": 2,
      "l": 0,
      "p": 0,
      "k": "default"
    },
    {
      "t": 9400,
      "d": 0,
      "l": 0,
      "p": 0,
      "k": "default"
    },
    {
      "t": 10200,
      "d": 2,
      "l": 0,
      "p": 1,
      "k": "default"
    },
    {
      "t": 11000,
      "d": 0,
      "l": 0,
      "p": 1,
      "k": "default"
    },
    {
      "t": 11400,
      "d": 0,
      "l": 0,
      "p": 1,
      "k": "default"
    },
    {
      "t": 11800,
      "d": 2,
      "l": 0,
      "p": 1,
      "k": "default"
    },
    {
      "t": 12600,
      "d": 0,
      "l": 0,
      "p": 1,
      "k": "default"
    },
    {
      "t": 13400,
      "d": 2,
      "l": 0,
      "p": 1,
      "k": "default"
    },
    {
      "t": 14200,
      "d": 0,
      "l": 0,
      "p": 1,
      "k": "default"
    },
    {
      "t": 14600,
      "d": 0,
      "l": 0,
      "p": 1,
      "k": "default"
    },
    {
      "t": 15000,
      "d": 2,
      "l": 0,
      "p": 1,
      "k": "default"
    },
    {
      "t": 15800,
      "d": 0,
      "l": 0,
      "p": 1,
      "k": "default"
    },
    {
      "t": 16200,
      "d": 2,
      "l": 0,
      "p": 0,
      "k": "default"
    },
    {
      "t": 16800,
      "d": 3,
      "l": 0,
      "p": 0,
      "k": "default"
    },
    {
      "t": 17200,
      "d": 1,
      "l": 0,
      "p": 0,
      "k": "default"
    },
    {
      "t": 17800,
      "d": 3,
      "l": 0,
      "p": 0,
      "k": "default"
    },
    {
      "t": 18400,
      "d": 2,
      "l": 0,
      "p": 0,
      "k": "default"
    },
    {
      "t": 18800,
      "d": 1,
      "l": 0,
      "p": 0,
      "k": "default"
    },
    {
      "t": 19400,
      "d": 3,
      "l": 0,
      "p": 0,
      "k": "default"
    },
    {
      "t": 20000,
      "d": 2,
      "l": 0,
      "p": 0,
      "k": "default"
    },
    {
      "t": 20400,
      "d": 1,
      "l": 0,
      "p": 0,
      "k": "default"
    },
    {
      "t": 21000,
      "d": 2,
      "l": 0,
      "p": 0,
      "k": "default"
    },
    {
      "t": 21600,
      "d": 3,
      "l": 0,
      "p": 0,
      "k": "default"
    },
    {
      "t": 22000,
      "d": 1,
      "l": 0,
      "p": 0,
      "k": "default"
    },
    {
      "t": 22600,
      "d": 2,
      "l": 0,
      "p": 1,
      "k": "default"
    },
    {
      "t": 23200,
      "d": 3,
      "l": 0,
      "p": 1,
      "k": "default"
    },
    {
      "t": 23600,
      "d": 1,
      "l": 0,
      "p": 1,
      "k": "default"
    },
    {
      "t": 24200,
      "d": 3,
      "l": 0,
      "p": 1,
      "k": "default"
    },
    {
      "t": 24800,
      "d": 2,
      "l": 0,
      "p": 1,
      "k": "default"
    },
    {
      "t": 25200,
      "d": 1,
      "l": 0,
      "p": 1,
      "k": "default"
    },
    {
      "t": 25800,
      "d": 3,
      "l": 0,
      "p": 1,
      "k": "default"
    },
    {
      "t": 26400,
      "d": 2,
      "l": 0,
      "p": 1,
      "k": "default"
    },
    {
      "t": 26800,
      "d": 1,
      "l": 0,
      "p": 1,
      "k": "default"
    },
    {
      "t": 27400,
      "d": 2,
      "l": 0,
      "p": 1,
      "k": "default"
    },
    {
      "t": 28000,
      "d": 3,
      "l": 0,
      "p": 1,
      "k": "default"
    },
    {
      "t": 28400,
      "d": 1,
      "l": 0,
      "p": 1,
      "k": "default"
    },
    {
      "t": 29000,
      "d": 0,
      "l": 0,
      "p": 0,
      "k": "default"
    },
    {
      "t": 29600,
      "d": 2,
      "l": 0,
      "p": 0,
      "k": "default"
    },
    {
      "t": 30000,
      "d": 1,
      "l": 0,
      "p": 0,
      "k": "default"
    },
    {
      "t": 30200,
      "d": 3,
      "l": 0,
      "p": 0,
      "k": "default"
    },
    {
      "t": 30400,
      "d": 2,
      "l": 0,
      "p": 0,
      "k": "default"
    },
    {
      "t": 30600,
      "d": 3,
      "l": 0,
      "p": 0,
      "k": "default"
    },
    {
      "t": 30800,
      "d": 3,
      "l": 0,
      "p": 0,
      "k": "default"
    },
    {
      "t": 31200,
      "d": 0,
      "l": 300,
      "p": 0,
      "k": "default"
    },
    {
      "t": 31600,
      "d": 1,
      "l": 200,
      "p": 0,
      "k": "default"
    },
    {
      "t": 32200,
      "d": 3,
      "l": 0,
      "p": 0,
      "k": "default"
    },
    {
      "t": 32800,
      "d": 3,
      "l": 0,
      "p": 0,
      "k": "default"
    },
    {
      "t": 33200,
      "d": 2,
      "l": 0,
      "p": 0,
      "k": "default"
    },
    {
      "t": 33600,
      "d": 0,
      "l": 0,
      "p": 0,
      "k": "default"
    },
    {
      "t": 34000,
      "d": 3,
      "l": 0,
      "p": 0,
      "k": "default"
    },
    {
      "t": 34400,
      "d": 2,
      "l": 300,
      "p": 0,
      "k": "default"
    },
    {
      "t": 34800,
      "d": 1,
      "l": 300,
      "p": 0,
      "k": "default"
    },
    {
      "t": 35400,
      "d": 0,
      "l": 0,
      "p": 1,
      "k": "default"
    },
    {
      "t": 36000,
      "d": 2,
      "l": 0,
      "p": 1,
      "k": "default"
    },
    {
      "t": 36400,
      "d": 1,
      "l": 0,
      "p": 1,
      "k": "default"
    },
    {
      "t": 36600,
      "d": 3,
      "l": 0,
      "p": 1,
      "k": "default"
    },
    {
      "t": 36800,
      "d": 2,
      "l": 0,
      "p": 1,
      "k": "default"
    },
    {
      "t": 37000,
      "d": 3,
      "l": 0,
      "p": 1,
      "k": "default"
    },
    {
      "t": 37200,
      "d": 3,
      "l": 0,
      "p": 1,
      "k": "default"
    },
    {
      "t": 37600,
      "d": 0,
      "l": 300,
      "p": 1,
      "k": "default"
    },
    {
      "t": 38000,
      "d": 1,
      "l": 200,
      "p": 1,
      "k": "default"
    },
    {
      "t": 38600,
      "d": 3,
      "l": 0,
      "p": 1,
      "k": "default"
    },
    {
      "t": 39200,
      "d": 3,
      "l": 0,
      "p": 1,
      "k": "default"
    },
    {
      "t": 39600,
      "d": 2,
      "l": 0,
      "p": 1,
      "k": "default"
    },
    {
      "t": 40000,
      "d": 0,
      "l": 0,
      "p": 1,
      "k": "default"
    },
    {
      "t": 40400,
      "d": 3,
      "l": 0,
      "p": 1,
      "k": "default"
    },
    {
      "t": 40800,
      "d": 2,
      "l": 300,
      "p": 1,
      "k": "default"
    },
    {
      "t": 41200,
      "d": 1,
      "l": 300,
      "p": 1,
      "k": "default"
    },
    {
      "t": 41800,
      "d": 2,
      "l": 0,
      "p": 0,
      "k": "default"
    },
    {
      "t": 42400,
      "d": 3,
      "l": 0,
      "p": 0,
      "k": "default"
    },
    {
      "t": 42800,
      "d": 1,
      "l": 0,
      "p": 0,
      "k": "default"
    },
    {
      "t": 43400,
      "d": 2,
      "l": 0,
      "p": 0,
      "k": "default"
    },
    {
      "t": 44000,
      "d": 3,
      "l": 0,
      "p": 0,
      "k": "default"
    },
    {
      "t": 44400,
      "d": 1,
      "l": 0,
      "p": 0,
      "k": "default"
    },
    {
      "t": 45000,
      "d": 3,
      "l": 0,
      "p": 0,
      "k": "default"
    },
    {
      "t": 45600,
      "d": 2,
      "l": 0,
      "p": 0,
      "k": "default"
    },
    {
      "t": 46000,
      "d": 1,
      "l": 0,
      "p": 0,
      "k": "default"
    },
    {
      "t": 46600,
      "d": 2,
      "l": 0,
      "p": 0,
      "k": "default"
    },
    {
      "t": 47200,
      "d": 3,
      "l": 0,
      "p": 0,
      "k": "default"
    },
    {
      "t": 47600,
      "d": 1,
      "l": 0,
      "p": 0,
      "k": "default"
    },
    {
      "t": 48200,
      "d": 2,
      "l": 0,
      "p": 1,
      "k": "default"
    },
    {
      "t": 48800,
      "d": 3,
      "l": 0,
      "p": 1,
      "k": "default"
    },
    {
      "t": 49200,
      "d": 1,
      "l": 0,
      "p": 1,
      "k": "default"
    },
    {
      "t": 49800,
      "d": 2,
      "l": 0,
      "p": 1,
      "k": "default"
    },
    {
      "t": 50400,
      "d": 3,
      "l": 0,
      "p": 1,
      "k": "default"
    },
    {
      "t": 50800,
      "d": 1,
      "l": 0,
      "p": 1,
      "k": "default"
    },
    {
      "t": 51400,
      "d": 3,
      "l": 0,
      "p": 1,
      "k": "default"
    },
    {
      "t": 52000,
      "d": 2,
      "l": 0,
      "p": 1,
      "k": "default"
    },
    {
      "t": 52400,
      "d": 1,
      "l": 0,
      "p": 1,
      "k": "default"
    },
    {
      "t": 53000,
      "d": 2,
      "l": 0,
      "p": 1,
      "k": "default"
    },
    {
      "t": 53600,
      "d": 3,
      "l": 0,
      "p": 1,
      "k": "default"
    },
    {
      "t": 54000,
      "d": 1,
      "l": 0,
      "p": 1,
      "k": "default"
    },
    {
      "t": 54400,
      "d": 2,
      "l": 200,
      "p": 1,
      "k": "default"
    },
    {
      "t": 54600,
      "d": 2,
      "l": 0,
      "p": 0,
      "k": "default"
    },
    {
      "t": 55000,
      "d": 3,
      "l": 0,
      "p": 1,
      "k": "default"
    },
    {
      "t": 55200,
      "d": 3,
      "l": 0,
      "p": 0,
      "k": "default"
    },
    {
      "t": 55200,
      "d": 1,
      "l": 0,
      "p": 1,
      "k": "default"
    },
    {
      "t": 55600,
      "d": 1,
      "l": 0,
      "p": 0,
      "k": "default"
    },
    {
      "t": 55600,
      "d": 3,
      "l": 0,
      "p": 1,
      "k": "default"
    },
    {
      "t": 56000,
      "d": 0,
      "l": 0,
      "p": 1,
      "k": "default"
    },
    {
      "t": 56200,
      "d": 0,
      "l": 0,
      "p": 0,
      "k": "default"
    },
    {
      "t": 56500,
      "d": 0,
      "l": 0,
      "p": 1,
      "k": "default"
    },
    {
      "t": 56800,
      "d": 3,
      "l": 0,
      "p": 0,
      "k": "default"
    },
    {
      "t": 56800,
      "d": 1,
      "l": 200,
      "p": 1,
      "k": "default"
    },
    {
      "t": 57200,
      "d": 2,
      "l": 0,
      "p": 0,
      "k": "default"
    },
    {
      "t": 57600,
      "d": 2,
      "l": 200,
      "p": 1,
      "k": "default"
    },
    {
      "t": 57800,
      "d": 3,
      "l": 0,
      "p": 0,
      "k": "default"
    },
    {
      "t": 58400,
      "d": 2,
      "l": 0,
      "p": 0,
      "k": "default"
    },
    {
      "t": 58400,
      "d": 1,
      "l": 0,
      "p": 1,
      "k": "default"
    },
    {
      "t": 58800,
      "d": 1,
      "l": 0,
      "p": 0,
      "k": "default"
    },
    {
      "t": 58800,
      "d": 3,
      "l": 0,
      "p": 1,
      "k": "default"
    },
    {
      "t": 59200,
      "d": 0,
      "l": 0,
      "p": 1,
      "k": "default"
    },
    {
      "t": 59400,
      "d": 0,
      "l": 0,
      "p": 0,
      "k": "default"
    },
    {
      "t": 59700,
      "d": 0,
      "l": 0,
      "p": 1,
      "k": "default"
    },
    {
      "t": 60000,
      "d": 3,
      "l": 0,
      "p": 0,
      "k": "default"
    },
    {
      "t": 60100,
      "d": 2,
      "l": 0,
      "p": 1,
      "k": "default"
    },
    {
      "t": 60400,
      "d": 2,
      "l": 0,
      "p": 0,
      "k": "default"
    },
    {
      "t": 60500,
      "d": 0,
      "l": 0,
      "p": 1,
      "k": "default"
    },
    {
      "t": 61000,
      "d": 2,
      "l": 0,
      "p": 1,
      "k": "default"
    },
    {
      "t": 61600,
      "d": 3,
      "l": 0,
      "p": 1,
      "k": "default"
    },
    {
      "t": 62000,
      "d": 1,
      "l": 0,
      "p": 1,
      "k": "default"
    },
    {
      "t": 62600,
      "d": 0,
      "l": 0,
      "p": 1,
      "k": "default"
    },
    {
      "t": 63200,
      "d": 3,
      "l": 0,
      "p": 1,
      "k": "default"
    },
    {
      "t": 63600,
      "d": 2,
      "l": 0,
      "p": 1,
      "k": "default"
    },
    {
      "t": 64200,
      "d": 3,
      "l": 0,
      "p": 1,
      "k": "default"
    },
    {
      "t": 64800,
      "d": 2,
      "l": 0,
      "p": 1,
      "k": "default"
    },
    {
      "t": 65200,
      "d": 1,
      "l": 0,
      "p": 1,
      "k": "default"
    },
    {
      "t": 65800,
      "d": 0,
      "l": 0,
      "p": 1,
      "k": "default"
    },
    {
      "t": 66400,
      "d": 3,
      "l": 0,
      "p": 1,
      "k": "default"
    },
    {
      "t": 66800,
      "d": 2,
      "l": 0,
      "p": 1,
      "k": "default"
    },
    {
      "t": 67400,
      "d": 0,
      "l": 0,
      "p": 0,
      "k": "default"
    },
    {
      "t": 68000,
      "d": 2,
      "l": 0,
      "p": 0,
      "k": "default"
    },
    {
      "t": 68400,
      "d": 1,
      "l": 0,
      "p": 0,
      "k": "default"
    },
    {
      "t": 68600,
      "d": 3,
      "l": 0,
      "p": 0,
      "k": "default"
    },
    {
      "t": 68800,
      "d": 2,
      "l": 0,
      "p": 0,
      "k": "default"
    },
    {
      "t": 69000,
      "d": 3,
      "l": 0,
      "p": 0,
      "k": "default"
    },
    {
      "t": 69200,
      "d": 3,
      "l": 0,
      "p": 0,
      "k": "default"
    },
    {
      "t": 69600,
      "d": 0,
      "l": 300,
      "p": 0,
      "k": "default"
    },
    {
      "t": 70000,
      "d": 1,
      "l": 200,
      "p": 0,
      "k": "default"
    },
    {
      "t": 70600,
      "d": 3,
      "l": 0,
      "p": 0,
      "k": "default"
    },
    {
      "t": 71200,
      "d": 3,
      "l": 0,
      "p": 0,
      "k": "default"
    },
    {
      "t": 71600,
      "d": 2,
      "l": 0,
      "p": 0,
      "k": "default"
    },
    {
      "t": 72000,
      "d": 0,
      "l": 0,
      "p": 0,
      "k": "default"
    },
    {
      "t": 72400,
      "d": 3,
      "l": 0,
      "p": 0,
      "k": "default"
    },
    {
      "t": 72800,
      "d": 2,
      "l": 300,
      "p": 0,
      "k": "default"
    },
    {
      "t": 73200,
      "d": 1,
      "l": 300,
      "p": 0,
      "k": "default"
    },
    {
      "t": 73800,
      "d": 0,
      "l": 0,
      "p": 1,
      "k": "default"
    },
    {
      "t": 74400,
      "d": 2,
      "l": 0,
      "p": 1,
      "k": "default"
    },
    {
      "t": 74800,
      "d": 1,
      "l": 0,
      "p": 1,
      "k": "default"
    },
    {
      "t": 75000,
      "d": 3,
      "l": 0,
      "p": 1,
      "k": "default"
    },
    {
      "t": 75200,
      "d": 2,
      "l": 0,
      "p": 1,
      "k": "default"
    },
    {
      "t": 75400,
      "d": 3,
      "l": 0,
      "p": 1,
      "k": "default"
    },
    {
      "t": 75600,
      "d": 3,
      "l": 0,
      "p": 1,
      "k": "default"
    },
    {
      "t": 76000,
      "d": 0,
      "l": 300,
      "p": 1,
      "k": "default"
    },
    {
      "t": 76400,
      "d": 1,
      "l": 200,
      "p": 1,
      "k": "default"
    },
    {
      "t": 77000,
      "d": 3,
      "l": 0,
      "p": 1,
      "k": "default"
    },
    {
      "t": 77600,
      "d": 3,
      "l": 0,
      "p": 1,
      "k": "default"
    },
    {
      "t": 78000,
      "d": 2,
      "l": 0,
      "p": 1,
      "k": "default"
    },
    {
      "t": 78400,
      "d": 0,
      "l": 0,
      "p": 1,
      "k": "default"
    },
    {
      "t": 78800,
      "d": 3,
      "l": 0,
      "p": 1,
      "k": "default"
    },
    {
      "t": 79200,
      "d": 2,
      "l": 300,
      "p": 1,
      "k": "default"
    },
    {
      "t": 79600,
      "d": 1,
      "l": 300,
      "p": 1,
      "k": "default"
    }
  ]
}